Metadata-Version: 2.1
Name: vng-api-common
Version: 2.0.5
Summary: VNG API tooling
Home-page: https://github.com/VNG-Realisatie/vng-api-common
Author: Maykin Media, VNG-Realisatie
Author-email: support@maykinmedia.nl
License: EUPL 1.2
Keywords: openapi,swagger,django,vng
Classifier: Development Status :: 5 - Production/Stable
Classifier: Framework :: Django
Classifier: Framework :: Django :: 2.2
Classifier: Framework :: Django :: 3.2
Classifier: Intended Audience :: Developers
Classifier: Operating System :: Unix
Classifier: Operating System :: MacOS
Classifier: Operating System :: Microsoft :: Windows
Classifier: Programming Language :: Python :: 3
Classifier: Programming Language :: Python :: 3 :: Only
Classifier: Programming Language :: Python :: 3.7
Classifier: Programming Language :: Python :: 3.8
Classifier: Programming Language :: Python :: 3.9
Classifier: Programming Language :: Python :: 3.10
Classifier: Topic :: Software Development :: Libraries :: Python Modules
Requires-Dist: django (<4.0,>=2.2.0)
Requires-Dist: django-choices
Requires-Dist: django-filter (>=2.0)
Requires-Dist: django-solo
Requires-Dist: djangorestframework (~=3.12.0)
Requires-Dist: djangorestframework-camel-case (>=1.2.0)
Requires-Dist: django-rest-framework-condition
Requires-Dist: drf-spectacular
Requires-Dist: drf-nested-routers (>=0.93.3)
Requires-Dist: gemma-zds-client (==1.0.1)
Requires-Dist: iso-639
Requires-Dist: isodate
Requires-Dist: notifications-api-common
Requires-Dist: oyaml
Requires-Dist: PyJWT
Requires-Dist: pyyaml
Requires-Dist: requests
Provides-Extra: coverage
Requires-Dist: pytest-cov ; extra == 'coverage'
Provides-Extra: docs
Requires-Dist: psycopg2 ; extra == 'docs'
Requires-Dist: sphinx ; extra == 'docs'
Requires-Dist: sphinx-rtd-theme ; extra == 'docs'
Provides-Extra: markdown_docs
Requires-Dist: django-markup (<=1.3) ; extra == 'markdown_docs'
Requires-Dist: markdown ; extra == 'markdown_docs'
Provides-Extra: notifications
Provides-Extra: pep8
Requires-Dist: flake8 ; extra == 'pep8'
Provides-Extra: release
Requires-Dist: bumpversion ; extra == 'release'
Provides-Extra: tests
Requires-Dist: psycopg2 ; extra == 'tests'
Requires-Dist: pytest ; extra == 'tests'
Requires-Dist: pytest-django ; extra == 'tests'
Requires-Dist: pytest-factoryboy ; extra == 'tests'
Requires-Dist: tox ; extra == 'tests'
Requires-Dist: isort ; extra == 'tests'
Requires-Dist: black ; extra == 'tests'
Requires-Dist: requests-mock ; extra == 'tests'
Requires-Dist: freezegun ; extra == 'tests'
